MANIFEST.in
README.md
setup.cfg
setup.py
django_i18nize/__init__.py
django_i18nize/apps.py
django_i18nize/settings.py
django_i18nize/utils.py
django_i18nize.egg-info/PKG-INFO
django_i18nize.egg-info/SOURCES.txt
django_i18nize.egg-info/dependency_links.txt
django_i18nize.egg-info/not-zip-safe
django_i18nize.egg-info/requires.txt
django_i18nize.egg-info/top_level.txt
django_i18nize/management/__init__.py
django_i18nize/management/commands/__init__.py
django_i18nize/management/commands/fetch_locale.py
django_i18nize/templatetags/__init__.py
django_i18nize/templatetags/i18nize_tags.py