Metadata-Version: 1.0
Name: django-i18nize
Version: 0.0.1
Summary: Django i18nize extends the i18nize python client. Template tag for rendering translation and Management command for fetching  translations is added.
Home-page: https://github.com/iktw/i18nize-django
Author: Mohammed Hammoud
Author-email: mohammed@iktw.se
License: MIT licence, see LICENCE.txt
Platform: UNKNOWN
